{
"skeleton": {
	"hash": "jZD+htk0Tbg",
	"spine": "4.0.64",
	"x": -245.72,
	"y": -202.1,
	"width": 512,
	"height": 512,
	"images": "",
	"audio": ""
},
"bones": [
	{ "name": "root" },
	{ "name": "100%", "parent": "root", "x": 2.44, "y": 50.58 },
	{ "name": "zimu", "parent": "root", "y": -29.55 },
	{ "name": "f", "parent": "zimu", "rotation": -2.68, "x": -58.41, "y": -11.72 },
	{ "name": "h", "parent": "zimu", "rotation": 5.49, "x": 66.43, "y": -11.92 },
	{ "name": "i", "parent": "zimu", "x": -30.66, "y": -14.41 },
	{ "name": "flag", "parent": "root", "x": 6.67, "y": 110.97 },
	{ "name": "jiantouzy", "parent": "root", "y": 110.32 },
	{ "name": "n", "parent": "zimu", "x": -5.23, "y": -16.93 },
	{ "name": "i2", "parent": "zimu", "x": 17.47, "y": -14.44 },
	{ "name": "piaodai_red", "parent": "root", "x": 2.72, "y": -31.59 },
	{ "name": "piaodai", "parent": "root", "x": 9.48, "y": -0.2 },
	{ "name": "s", "parent": "zimu", "x": 40.04, "y": -14.87 },
	{ "name": "100%2", "parent": "100%", "x": 7.5, "y": 2.13 },
	{ "name": "star", "parent": "root", "x": -162.69, "y": 69.56 },
	{ "name": "star2", "parent": "root", "x": 64.46, "y": -128.38 },
	{ "name": "star3", "parent": "root", "x": 42.82, "y": 147.44 },
	{ "name": "shine", "parent": "root", "x": 0.5, "y": 23.75 },
	{ "name": "shine2", "parent": "root", "x": 0.5, "y": 23.75 }
],
"slots": [
	{ "name": "shine", "bone": "shine", "attachment": "glow_010" },
	{ "name": "shine2", "bone": "shine2", "attachment": "glow_010" },
	{ "name": "qi2", "bone": "flag", "attachment": "qi2" },
	{ "name": "piaodai", "bone": "piaodai", "attachment": "piaodai" },
	{ "name": "piaodai2", "bone": "piaodai", "attachment": "piaodai" },
	{ "name": "qi", "bone": "flag", "attachment": "qi" },
	{ "name": "piaodai3", "bone": "piaodai_red", "attachment": "piaodai3" },
	{ "name": "fag", "bone": "100%", "attachment": "fag", "blend": "additive" },
	{ "name": "100%2", "bone": "100%2", "attachment": "100%", "blend": "additive" },
	{ "name": "100%", "bone": "100%", "attachment": "100%" },
	{ "name": "f", "bone": "f", "attachment": "f" },
	{ "name": "f2", "bone": "f", "color": "ffffff00", "attachment": "f", "blend": "additive" },
	{ "name": "h", "bone": "h", "attachment": "h" },
	{ "name": "h2", "bone": "h", "color": "ffffff00", "attachment": "h", "blend": "additive" },
	{ "name": "i", "bone": "i", "attachment": "i" },
	{ "name": "i3", "bone": "i", "color": "ffffff00", "attachment": "i", "blend": "additive" },
	{ "name": "i2", "bone": "i2", "attachment": "i2" },
	{ "name": "i4", "bone": "i2", "color": "ffffff00", "attachment": "i2", "blend": "additive" },
	{ "name": "jiantou", "bone": "jiantouzy", "attachment": "jiantou" },
	{ "name": "jiantou2", "bone": "jiantouzy", "attachment": "jiantou" },
	{ "name": "n", "bone": "n", "attachment": "n" },
	{ "name": "n2", "bone": "n", "color": "ffffff00", "attachment": "n", "blend": "additive" },
	{ "name": "s", "bone": "s", "attachment": "s" },
	{ "name": "s2", "bone": "s", "color": "ffffff00", "attachment": "s", "blend": "additive" },
	{ "name": "star", "bone": "star", "attachment": "star0" },
	{ "name": "star2", "bone": "star2", "attachment": "star0" },
	{ "name": "star3", "bone": "star3", "attachment": "star0" }
],
"skins": [
	{
		"name": "default",
		"attachments": {
			"100%": {
				"100%": { "x": 7.5, "y": 2.13, "width": 182, "height": 65 }
			},
			"100%2": {
				"100%": { "width": 182, "height": 65 }
			},
			"f": {
				"f": { "x": 6.02, "y": 16.55, "rotation": 2.68, "width": 28, "height": 39 }
			},
			"f2": {
				"f": { "x": 6.02, "y": 16.55, "rotation": 2.68, "width": 28, "height": 39 }
			},
			"fag": {
				"fag": { "x": 7.84, "y": 3.32, "width": 512, "height": 512 }
			},
			"h": {
				"h": { "x": 1.56, "y": 16.22, "rotation": -5.49, "width": 30, "height": 38 }
			},
			"h2": {
				"h": { "x": 1.56, "y": 16.22, "rotation": -5.49, "width": 30, "height": 38 }
			},
			"i": {
				"i": { "x": 1.64, "y": 17.11, "width": 17, "height": 39 }
			},
			"i2": {
				"i2": { "y": 15.5, "width": 15, "height": 38 }
			},
			"i3": {
				"i": { "x": 1.64, "y": 17.11, "width": 17, "height": 39 }
			},
			"i4": {
				"i2": { "y": 15.5, "width": 15, "height": 38 }
			},
			"jiantou": {
				"jiantou": { "x": -113.39, "y": -6.47, "width": 38, "height": 48 }
			},
			"jiantou2": {
				"jiantou": { "x": 126.45, "y": -6.52, "scaleX": -1, "width": 38, "height": 48 }
			},
			"n": {
				"n": { "x": -0.73, "y": 13.45, "width": 29, "height": 29 }
			},
			"n2": {
				"n": { "x": -0.73, "y": 13.45, "width": 29, "height": 29 }
			},
			"piaodai": {
				"piaodai": { "x": 109.07, "y": -0.01, "rotation": 1.73, "width": 73, "height": 58 }
			},
			"piaodai2": {
				"piaodai": { "x": -114.39, "y": 3.84, "scaleX": -1, "rotation": 0.01, "width": 73, "height": 58 }
			},
			"piaodai3": {
				"piaodai3": { "x": 3.73, "y": 11.66, "width": 240, "height": 77 }
			},
			"qi": {
				"qi": { "x": -0.29, "y": -95.53, "width": 207, "height": 214 }
			},
			"qi2": {
				"qi2": { "x": -0.57, "y": -107.24, "width": 189, "height": 208 }
			},
			"s": {
				"s": { "y": 12.04, "width": 25, "height": 30 }
			},
			"s2": {
				"s": { "y": 12.04, "width": 25, "height": 30 }
			},
			"shine": {
				"glow_010": { "scaleX": 0.88, "scaleY": 0.88, "width": 512, "height": 512 }
			},
			"shine2": {
				"glow_010": { "scaleX": 0.88, "scaleY": 0.88, "width": 512, "height": 512 }
			},
			"star": {
				"star0": { "width": 128, "height": 128 }
			},
			"star2": {
				"star0": { "width": 128, "height": 128 }
			},
			"star3": {
				"star0": { "width": 128, "height": 128 }
			}
		}
	}
],
"animations": {
	"animation": {
		"slots": {
			"100%": {
				"rgba": [
					{ "color": "ffffff00", "curve": "stepped" },
					{
						"time": 0.5667,
						"color": "ffffff00",
						"curve": [ 0.611, 1, 0.656, 1, 0.611, 1, 0.656, 1, 0.611, 1, 0.656, 1, 0.611, 0, 0.656, 0.67 ]
					},
					{ "time": 0.7, "color": "fffffffe" }
				]
			},
			"100%2": {
				"rgba": [
					{
						"color": "ffffff00",
						"curve": [ 0.189, 1, 0.378, 1, 0.189, 1, 0.378, 1, 0.189, 1, 0.378, 1, 0.189, 0, 0.543, -0.23 ]
					},
					{
						"time": 0.5667,
						"color": "ffffff00",
						"curve": [ 0.611, 1, 0.656, 1, 0.611, 1, 0.656, 1, 0.611, 1, 0.656, 1, 0.601, 0.34, 0.634, 1 ]
					},
					{
						"time": 0.7,
						"color": "fffffffe",
						"curve": [ 0.822, 1, 0.944, 1, 0.822, 1, 0.944, 1, 0.822, 1, 0.944, 1, 0.945, 0.98, 1.008, 0.35 ]
					},
					{ "time": 1.0667, "color": "ffffff00" }
				]
			},
			"f": {
				"rgba": [
					{ "color": "ffffff00", "curve": "stepped" },
					{
						"time": 1.1,
						"color": "ffffff00",
						"curve": [ 1.156, 1, 1.178, 1, 1.156, 1, 1.178, 1, 1.156, 1, 1.178, 1, 1.156, 0, 1.178, 1 ]
					},
					{ "time": 1.2333, "color": "ffffffff" }
				]
			},
			"f2": {
				"rgba": [
					{ "color": "ffffff00", "curve": "stepped" },
					{
						"time": 1.1,
						"color": "ffffff00",
						"curve": [ 1.156, 1, 1.178, 1, 1.156, 1, 1.178, 1, 1.156, 1, 1.178, 1, 1.156, 0, 1.178, 1 ]
					},
					{
						"time": 1.2333,
						"color": "ffffffff",
						"curve": [ 1.289, 1, 1.344, 1, 1.289, 1, 1.344, 1, 1.289, 1, 1.344, 1, 1.289, 1, 1.344, 0 ]
					},
					{ "time": 1.4, "color": "ffffff00" }
				]
			},
			"fag": {
				"rgba": [
					{ "color": "ffffff00", "curve": "stepped" },
					{ "time": 0.7, "color": "ffffff00" },
					{ "time": 0.8333, "color": "ffffffff" },
					{ "time": 1.4667, "color": "ffffff00" }
				]
			},
			"h": {
				"rgba": [
					{ "color": "ffffff00", "curve": "stepped" },
					{
						"time": 1.5667,
						"color": "ffffff00",
						"curve": [ 1.622, 1, 1.644, 1, 1.622, 1, 1.644, 1, 1.622, 1, 1.644, 1, 1.622, 0, 1.644, 1 ]
					},
					{ "time": 1.7, "color": "ffffffff" }
				]
			},
			"h2": {
				"rgba": [
					{ "color": "ffffff00", "curve": "stepped" },
					{
						"time": 1.5667,
						"color": "ffffff00",
						"curve": [ 1.622, 1, 1.644, 1, 1.622, 1, 1.644, 1, 1.622, 1, 1.644, 1, 1.622, 0, 1.644, 1 ]
					},
					{
						"time": 1.7,
						"color": "ffffffff",
						"curve": [ 1.767, 1, 1.833, 1, 1.767, 1, 1.833, 1, 1.767, 1, 1.833, 1, 1.767, 1, 1.833, 0 ]
					},
					{ "time": 1.9, "color": "ffffff00" }
				]
			},
			"i": {
				"rgba": [
					{ "color": "ffffff00", "curve": "stepped" },
					{
						"time": 1.1667,
						"color": "ffffff00",
						"curve": [ 1.222, 1, 1.311, 1, 1.222, 1, 1.311, 1, 1.222, 1, 1.311, 1, 1.222, 0, 1.311, 1 ]
					},
					{ "time": 1.3667, "color": "ffffffff" }
				]
			},
			"i2": {
				"rgba": [
					{ "color": "ffffff00", "curve": "stepped" },
					{
						"time": 1.3667,
						"color": "ffffff00",
						"curve": [ 1.422, 1, 1.478, 1, 1.422, 1, 1.478, 1, 1.422, 1, 1.478, 1, 1.422, 0, 1.478, 1 ]
					},
					{ "time": 1.5333, "color": "ffffffff" }
				]
			},
			"i3": {
				"rgba": [
					{ "color": "ffffff00", "curve": "stepped" },
					{
						"time": 1.1667,
						"color": "ffffff00",
						"curve": [ 1.222, 1, 1.311, 1, 1.222, 1, 1.311, 1, 1.222, 1, 1.311, 1, 1.222, 0, 1.311, 1 ]
					},
					{
						"time": 1.3667,
						"color": "ffffffff",
						"curve": [ 1.422, 1, 1.478, 1, 1.422, 1, 1.478, 1, 1.422, 1, 1.478, 1, 1.422, 1, 1.478, 0 ]
					},
					{ "time": 1.5333, "color": "ffffff00" }
				]
			},
			"i4": {
				"rgba": [
					{ "color": "ffffff00", "curve": "stepped" },
					{
						"time": 1.3667,
						"color": "ffffff00",
						"curve": [ 1.422, 1, 1.478, 1, 1.422, 1, 1.478, 1, 1.422, 1, 1.478, 1, 1.422, 0, 1.478, 1 ]
					},
					{
						"time": 1.5333,
						"color": "ffffffff",
						"curve": [ 1.589, 1, 1.644, 1, 1.589, 1, 1.644, 1, 1.589, 1, 1.644, 1, 1.589, 1, 1.644, 0 ]
					},
					{ "time": 1.7, "color": "ffffff00" }
				]
			},
			"jiantou": {
				"rgba": [
					{
						"color": "ffffff00",
						"curve": [ 0.111, 1, -0.011, 1, 0.111, 1, -0.011, 1, 0.111, 1, -0.011, 1, 0.111, 0, -0.011, 1 ]
					},
					{ "time": 0.1, "color": "ffffffff" }
				]
			},
			"jiantou2": {
				"rgba": [
					{
						"color": "ffffff00",
						"curve": [ 0.111, 1, -0.011, 1, 0.111, 1, -0.011, 1, 0.111, 1, -0.011, 1, 0.111, 0, -0.011, 1 ]
					},
					{ "time": 0.1, "color": "ffffffff" }
				]
			},
			"n": {
				"rgba": [
					{ "color": "ffffff00", "curve": "stepped" },
					{
						"time": 1.2667,
						"color": "ffffff00",
						"curve": [ 1.322, 1, 1.378, 1, 1.322, 1, 1.378, 1, 1.322, 1, 1.378, 1, 1.322, 0, 1.378, 1 ]
					},
					{ "time": 1.4333, "color": "ffffffff" }
				]
			},
			"n2": {
				"rgba": [
					{ "color": "ffffff00", "curve": "stepped" },
					{
						"time": 1.2667,
						"color": "ffffff00",
						"curve": [ 1.322, 1, 1.378, 1, 1.322, 1, 1.378, 1, 1.322, 1, 1.378, 1, 1.322, 0, 1.378, 1 ]
					},
					{
						"time": 1.4333,
						"color": "ffffffff",
						"curve": [ 1.489, 1, 1.544, 1, 1.489, 1, 1.544, 1, 1.489, 1, 1.544, 1, 1.489, 1, 1.544, 0 ]
					},
					{ "time": 1.6, "color": "ffffff00" }
				]
			},
			"piaodai": {
				"rgba": [
					{ "color": "ffffff00", "curve": "stepped" },
					{
						"time": 0.6667,
						"color": "ffffff00",
						"curve": [ 0.733, 1, 0.8, 1, 0.733, 1, 0.8, 1, 0.733, 1, 0.8, 1, 0.733, 0, 0.8, 0.67 ]
					},
					{ "time": 0.8667, "color": "ffffffff" }
				]
			},
			"piaodai2": {
				"rgba": [
					{ "color": "ffffff00", "curve": "stepped" },
					{
						"time": 0.6667,
						"color": "ffffff00",
						"curve": [ 0.733, 1, 0.8, 1, 0.733, 1, 0.8, 1, 0.733, 1, 0.8, 1, 0.733, 0, 0.8, 0.67 ]
					},
					{ "time": 0.8667, "color": "ffffffff" }
				]
			},
			"piaodai3": {
				"rgba": [
					{ "color": "ffffff00", "curve": "stepped" },
					{
						"time": 0.7333,
						"color": "ffffff00",
						"curve": [ 0.778, 1, 0.822, 1, 0.778, 1, 0.822, 1, 0.778, 1, 0.822, 1, 0.778, 0, 0.822, 0.67 ]
					},
					{ "time": 0.8667, "color": "ffffffff" }
				]
			},
			"qi": {
				"rgba": [
					{ "color": "ffffff00", "curve": "stepped" },
					{ "time": 0.1667, "color": "ffffff00" },
					{ "time": 0.2, "color": "fffffffe" }
				]
			},
			"qi2": {
				"rgba": [
					{ "color": "ffffff00", "curve": "stepped" },
					{ "time": 0.1667, "color": "ffffff00" },
					{ "time": 0.2, "color": "fffffffe" }
				]
			},
			"s": {
				"rgba": [
					{ "color": "ffffff00", "curve": "stepped" },
					{
						"time": 1.4667,
						"color": "ffffff00",
						"curve": [ 1.522, 1, 1.578, 1, 1.522, 1, 1.578, 1, 1.522, 1, 1.578, 1, 1.522, 0, 1.578, 1 ]
					},
					{ "time": 1.6333, "color": "ffffffff" }
				]
			},
			"s2": {
				"rgba": [
					{ "color": "ffffff00", "curve": "stepped" },
					{
						"time": 1.4667,
						"color": "ffffff00",
						"curve": [ 1.522, 1, 1.578, 1, 1.522, 1, 1.578, 1, 1.522, 1, 1.578, 1, 1.522, 0, 1.578, 1 ]
					},
					{
						"time": 1.6333,
						"color": "ffffffff",
						"curve": [ 1.689, 1, 1.744, 1, 1.689, 1, 1.744, 1, 1.689, 1, 1.744, 1, 1.689, 1, 1.744, 0 ]
					},
					{ "time": 1.8, "color": "ffffff00" }
				]
			},
			"shine": {
				"rgba": [
					{ "color": "ffffff00", "curve": "stepped" },
					{ "time": 0.6667, "color": "ffffff00" },
					{ "time": 1, "color": "ffffffff" }
				]
			},
			"shine2": {
				"rgba": [
					{ "color": "ffffff00", "curve": "stepped" },
					{ "time": 0.6667, "color": "ffffff00" },
					{ "time": 1, "color": "ffffffff" }
				]
			},
			"star": {
				"rgba": [
					{ "color": "ffffff00", "curve": "stepped" },
					{
						"time": 0.6667,
						"color": "ffffff00",
						"curve": [ 0.687, 1, 0.746, 1, 0.687, 1, 0.746, 1, 0.687, 1, 0.746, 1, 0.687, 0, 0.746, 1 ]
					},
					{ "time": 0.7667, "color": "ffffffff", "curve": "stepped" },
					{
						"time": 1.2333,
						"color": "ffffffff",
						"curve": [ 1.264, 1, 1.403, 1, 1.264, 1, 1.403, 1, 1.264, 1, 1.403, 1, 1.264, 1, 1.403, 0.33 ]
					},
					{ "time": 1.4333, "color": "ffffff00" }
				]
			},
			"star2": {
				"rgba": [
					{ "color": "ffffff00", "curve": "stepped" },
					{
						"time": 1,
						"color": "ffffff00",
						"curve": [ 1.02, 1, 1.08, 1, 1.02, 1, 1.08, 1, 1.02, 1, 1.08, 1, 1.02, 0, 1.08, 1 ]
					},
					{ "time": 1.1, "color": "ffffffff", "curve": "stepped" },
					{
						"time": 1.5667,
						"color": "ffffffff",
						"curve": [ 1.597, 1, 1.736, 1, 1.597, 1, 1.736, 1, 1.597, 1, 1.736, 1, 1.597, 1, 1.736, 0.33 ]
					},
					{ "time": 1.7667, "color": "ffffff00" }
				]
			},
			"star3": {
				"rgba": [
					{ "color": "ffffff00", "curve": "stepped" },
					{
						"time": 1.4,
						"color": "ffffff00",
						"curve": [ 1.415, 1, 1.452, 1, 1.415, 1, 1.452, 1, 1.415, 1, 1.452, 1, 1.415, 0, 1.452, 1 ]
					},
					{ "time": 1.4667, "color": "ffffffff", "curve": "stepped" },
					{
						"time": 1.8,
						"color": "ffffffff",
						"curve": [ 1.822, 1, 1.911, 1, 1.822, 1, 1.911, 1, 1.822, 1, 1.911, 1, 1.822, 1, 1.911, 0.33 ]
					},
					{ "time": 1.9333, "color": "ffffff00" }
				]
			}
		},
		"bones": {
			"jiantouzy": {
				"scale": [
					{
						"x": 1.3,
						"curve": [ 0.222, 1.3, 0.044, 1, 0.222, 1, 0.044, 1 ]
					},
					{ "time": 0.2667 }
				]
			},
			"flag": {
				"scale": [
					{
						"y": 0.1,
						"curve": [ 0.078, 1, 0.156, 1, 0.078, 0.1, 0.156, -0.207 ]
					},
					{
						"time": 0.2333,
						"y": 0.1,
						"curve": [ 0.326, 1, 0.329, 1, 0.326, 0.467, 0.31, 1.183 ]
					},
					{
						"time": 0.4333,
						"y": 1.2,
						"curve": [ 0.5, 1, 0.567, 1, 0.535, 1.214, 0.567, 0.95 ]
					},
					{
						"time": 0.6333,
						"y": 0.95,
						"curve": [ 0.7, 1, 0.799, 1.001, 0.741, 0.95, 0.77, 1.06 ]
					},
					{
						"time": 0.8333,
						"y": 1.05,
						"curve": [ 0.879, 0.998, 0.944, 1, 0.92, 1.037, 0.946, 1.017 ]
					},
					{ "time": 1 }
				]
			},
			"piaodai_red": {
				"scale": [
					{ "x": 1.2, "y": 1.2, "curve": "stepped" },
					{
						"time": 0.7333,
						"x": 1.2,
						"y": 1.2,
						"curve": [ 0.778, 1.2, 0.822, 0.98, 0.778, 1.2, 0.822, 0.98 ]
					},
					{
						"time": 0.8667,
						"x": 0.98,
						"y": 0.98,
						"curve": [ 0.933, 0.98, 1, 0.993, 0.933, 0.98, 1, 0.993 ]
					},
					{ "time": 1.0667 }
				]
			},
			"piaodai": {
				"scale": [
					{
						"x": 0.719,
						"curve": [ 0.222, 0.719, 0.583, 0.169, 0.222, 1, 0.444, 0.889 ]
					},
					{
						"time": 0.6667,
						"x": 0.444,
						"curve": [ 0.733, 0.663, 0.8, 1.1, 0.733, 1.033, 0.8, 1.1 ]
					},
					{
						"time": 0.8667,
						"x": 1.1,
						"y": 1.1,
						"curve": [ 0.933, 1.1, 1, 0.98, 0.933, 1.1, 1, 0.95 ]
					},
					{
						"time": 1.0667,
						"x": 0.98,
						"y": 0.95,
						"curve": [ 1.133, 0.98, 1.2, 1.02, 1.133, 0.95, 1.2, 1.02 ]
					},
					{
						"time": 1.2667,
						"x": 1.02,
						"y": 1.02,
						"curve": [ 1.333, 1.02, 1.4, 1.007, 1.333, 1.02, 1.4, 1.007 ]
					},
					{ "time": 1.4667 }
				]
			},
			"100%": {
				"scale": [
					{ "x": 1.5, "y": 1.5, "curve": "stepped" },
					{
						"time": 0.5667,
						"x": 1.5,
						"y": 1.5,
						"curve": [ 0.611, 1.5, 0.656, 1, 0.611, 1.5, 0.656, 1 ]
					},
					{ "time": 0.7 }
				]
			},
			"f": {
				"translate": [
					{
						"time": 1.1,
						"curve": [ 1.156, 0.1, 1.178, 0.3, 1.156, 2.12, 1.178, 6.37 ]
					},
					{
						"time": 1.2333,
						"x": 0.3,
						"y": 6.37,
						"curve": [ 1.289, 0.3, 1.344, 0.1, 1.289, 6.37, 1.344, 2.12 ]
					},
					{ "time": 1.4 }
				],
				"scale": [
					{
						"time": 1.1,
						"x": 0.1,
						"y": 0.1,
						"curve": [ 1.156, 0.433, 1.178, 1.1, 1.156, 0.467, 1.178, 1.2 ]
					},
					{
						"time": 1.2333,
						"x": 1.1,
						"y": 1.2,
						"curve": [ 1.289, 1.1, 1.344, 1.033, 1.289, 1.2, 1.344, 1.067 ]
					},
					{ "time": 1.4 }
				]
			},
			"h": {
				"translate": [
					{
						"time": 1.5667,
						"curve": [ 1.622, -0.2, 1.644, -0.61, 1.622, 2.12, 1.644, 6.35 ]
					},
					{
						"time": 1.7,
						"x": -0.61,
						"y": 6.35,
						"curve": [ 1.756, -0.61, 1.844, -0.2, 1.756, 6.35, 1.844, 2.12 ]
					},
					{ "time": 1.9 }
				],
				"scale": [
					{
						"time": 1.5667,
						"x": 0.1,
						"y": 0.1,
						"curve": [ 1.622, 0.433, 1.644, 1.1, 1.622, 0.467, 1.644, 1.2 ]
					},
					{
						"time": 1.7,
						"x": 1.1,
						"y": 1.2,
						"curve": [ 1.756, 1.1, 1.844, 1.033, 1.756, 1.2, 1.844, 1.067 ]
					},
					{ "time": 1.9 }
				]
			},
			"i": {
				"translate": [
					{
						"time": 1.1667,
						"curve": [ 1.222, 0, 1.311, 0, 1.222, 2.13, 1.311, 6.38 ]
					},
					{
						"time": 1.3667,
						"y": 6.38,
						"curve": [ 1.422, 0, 1.478, 0, 1.422, 6.38, 1.478, 2.13 ]
					},
					{ "time": 1.5333 }
				],
				"scale": [
					{
						"time": 1.1667,
						"x": 0.1,
						"y": 0.1,
						"curve": [ 1.222, 0.433, 1.311, 1.1, 1.222, 0.467, 1.311, 1.2 ]
					},
					{
						"time": 1.3667,
						"x": 1.1,
						"y": 1.2,
						"curve": [ 1.422, 1.1, 1.478, 1.033, 1.422, 1.2, 1.478, 1.067 ]
					},
					{ "time": 1.5333 }
				]
			},
			"n": {
				"translate": [
					{
						"time": 1.2667,
						"curve": [ 1.322, 0, 1.378, 0, 1.322, 2.13, 1.378, 6.38 ]
					},
					{
						"time": 1.4333,
						"y": 6.38,
						"curve": [ 1.489, 0, 1.544, 0, 1.489, 6.38, 1.544, 2.13 ]
					},
					{ "time": 1.6 }
				],
				"scale": [
					{
						"time": 1.2667,
						"x": 0.1,
						"y": 0.1,
						"curve": [ 1.322, 0.433, 1.378, 1.1, 1.322, 0.467, 1.378, 1.2 ]
					},
					{
						"time": 1.4333,
						"x": 1.1,
						"y": 1.2,
						"curve": [ 1.489, 1.1, 1.544, 1.033, 1.489, 1.2, 1.544, 1.067 ]
					},
					{ "time": 1.6 }
				]
			},
			"i2": {
				"translate": [
					{
						"time": 1.3667,
						"curve": [ 1.422, 0, 1.478, 0, 1.422, 2.13, 1.478, 6.38 ]
					},
					{
						"time": 1.5333,
						"y": 6.38,
						"curve": [ 1.589, 0, 1.644, 0, 1.589, 6.38, 1.644, 2.13 ]
					},
					{ "time": 1.7 }
				],
				"scale": [
					{
						"time": 1.3667,
						"x": 0.1,
						"y": 0.1,
						"curve": [ 1.422, 0.433, 1.478, 1.1, 1.422, 0.467, 1.478, 1.2 ]
					},
					{
						"time": 1.5333,
						"x": 1.1,
						"y": 1.2,
						"curve": [ 1.589, 1.1, 1.644, 1.033, 1.589, 1.2, 1.644, 1.067 ]
					},
					{ "time": 1.7 }
				]
			},
			"s": {
				"translate": [
					{
						"time": 1.4667,
						"curve": [ 1.522, 0, 1.578, 0, 1.522, 2.13, 1.578, 6.38 ]
					},
					{
						"time": 1.6333,
						"y": 6.38,
						"curve": [ 1.689, 0, 1.744, 0, 1.689, 6.38, 1.744, 2.13 ]
					},
					{ "time": 1.8 }
				],
				"scale": [
					{
						"time": 1.4667,
						"x": 0.1,
						"y": 0.1,
						"curve": [ 1.522, 0.433, 1.578, 1.1, 1.522, 0.467, 1.578, 1.2 ]
					},
					{
						"time": 1.6333,
						"x": 1.1,
						"y": 1.2,
						"curve": [ 1.689, 1.1, 1.744, 1.033, 1.689, 1.2, 1.744, 1.067 ]
					},
					{ "time": 1.8 }
				]
			},
			"100%2": {
				"scale": [
					{
						"time": 0.7,
						"curve": [ 0.844, 1, 0.989, 1.5, 0.844, 1, 0.989, 1.5 ]
					},
					{ "time": 1.1333, "x": 1.5, "y": 1.5 }
				]
			},
			"star": {
				"scale": [
					{ "x": 0.1, "y": 0.1, "curve": "stepped" },
					{
						"time": 0.6667,
						"x": 0.1,
						"y": 0.1,
						"curve": [ 0.818, 0.1, 0.882, 1.1, 0.818, 0.1, 0.882, 1.1 ]
					},
					{
						"time": 1.0333,
						"x": 1.1,
						"y": 1.1,
						"curve": [ 1.134, 1.1, 1.399, 1, 1.134, 1.1, 1.399, 1 ]
					},
					{ "time": 1.5 }
				]
			},
			"star2": {
				"scale": [
					{ "x": 0.1, "y": 0.1, "curve": "stepped" },
					{
						"time": 1,
						"x": 0.1,
						"y": 0.1,
						"curve": [ 1.152, 0.1, 1.215, 0.8, 1.152, 0.1, 1.215, 0.8 ]
					},
					{
						"time": 1.3667,
						"x": 0.8,
						"y": 0.8,
						"curve": [ 1.468, 0.8, 1.732, 1, 1.468, 0.8, 1.732, 1 ]
					},
					{ "time": 1.8333 }
				]
			},
			"star3": {
				"scale": [
					{ "x": 0.1, "y": 0.1, "curve": "stepped" },
					{
						"time": 1.4,
						"x": 0.1,
						"y": 0.1,
						"curve": [ 1.51, 0.1, 1.557, 0.9, 1.51, 0.1, 1.557, 0.9 ]
					},
					{
						"time": 1.6667,
						"x": 0.9,
						"y": 0.9,
						"curve": [ 1.74, 0.9, 1.927, 1, 1.74, 0.9, 1.927, 1 ]
					},
					{ "time": 2 }
				]
			},
			"shine": {
				"rotate": [
					{ "time": 0.6667 },
					{ "time": 2, "value": 45 }
				],
				"scale": [
					{
						"time": 0.6667,
						"x": 0.5,
						"y": 0.5,
						"curve": [ 0.778, 0.667, 0.889, 1.1, 0.778, 0.667, 0.889, 1.1 ]
					},
					{
						"time": 1,
						"x": 1.1,
						"y": 1.1,
						"curve": [ 1.167, 1.1, 1.333, 0.8, 1.167, 1.1, 1.333, 0.8 ]
					},
					{
						"time": 1.5,
						"x": 0.8,
						"y": 0.8,
						"curve": [ 1.667, 0.8, 1.833, 0.967, 1.667, 0.8, 1.833, 0.967 ]
					},
					{ "time": 2 }
				]
			},
			"shine2": {
				"rotate": [
					{ "time": 0.6667, "curve": "stepped" },
					{ "time": 2 }
				],
				"scale": [
					{
						"time": 0.6667,
						"x": 0.5,
						"y": 0.5,
						"curve": [ 0.778, 0.667, 0.833, 0.8, 0.778, 0.667, 0.833, 0.8 ]
					},
					{
						"time": 1,
						"x": 0.8,
						"y": 0.8,
						"curve": [ 1.167, 0.8, 1.356, 1, 1.167, 0.8, 1.356, 1 ]
					},
					{
						"time": 1.4667,
						"curve": [ 1.633, 1, 1.833, 0.967, 1.633, 1, 1.833, 0.967 ]
					},
					{ "time": 2 }
				]
			}
		}
	}
}
}